LICENSE
README.md
setup.py
chorder/__init__.py
chorder/acchorder.py
chorder/chord.py
chorder/dechorder.py
chorder/timepoints.py
chorder_py.egg-info/PKG-INFO
chorder_py.egg-info/SOURCES.txt
chorder_py.egg-info/dependency_links.txt
chorder_py.egg-info/top_level.txt