Metadata-Version: 2.1
Name: chorder-py
Version: 1.0.0
Summary: A modified version of chorder with drums fix
Home-page: https://github.com/tuneflow/chorder-py
Author: TuneFlow
Author-email: contact@info.tuneflow.com
License: UNKNOWN
Platform: UNKNOWN
Classifier: Programming Language :: Python :: 3
Classifier: License :: OSI Approved :: MIT License
Classifier: Operating System :: OS Independent
Requires-Python: >=3.7
License-File: LICENSE
